{
  "name": "Volo.Abp.SettingManagement.HttpApi.Client",
  "hash": "76fef83ae8b48071528b1858d0cdc76f",
  "contents": [
    {
      "namespace": "Volo.Abp.SettingManagement",
      "dependsOnModules": [
        {
          "declaringAssemblyName": "Volo.Abp.SettingManagement.Application.Contracts",
          "namespace": "Volo.Abp.SettingManagement",
          "name": "AbpSettingManagementApplicationContractsModule"
        },
        {
          "declaringAssemblyName": "Volo.Abp.Http.Client",
          "namespace": "Volo.Abp.Http.Client",
          "name": "AbpHttpClientModule"
        }
      ],
      "contentType": "abpModule",
      "name": "AbpSettingManagementHttpApiClientModule",
      "summary": null
    }
  ]
}