{
  "parameters": [
    {
      "name": "UI",
      "displayName": "UI",
      "values": {
        "MVC": "MVC / Razor Pages",
        "Blazor": "Blazor WebAssembly",
        "BlazorServer": "Blazor Server",
        "NG": "Angular"
      }
    },
    {
      "name": "DB",
      "displayName": "Database",
      "values": {
        "EF": "Entity Framework Core",
        "Mongo": "MongoDB"
      }
    },
    {
      "name": "Tiered",
      "displayName": "Tiered",
      "values": {
        "No": "Not Tiered",
        "Yes": "Tiered"
      }
    }
  ]
}