{
  "culture": "hi",
  "texts": {
    "Volo.AbpIo.Domain:010004": "अधिकतम सदस्य संख्या तक पहुँच गया!",
    "Volo.AbpIo.Domain:010005": "अधिकतम मालिक की गिनती तक पहुँच गया!",
    "Volo.AbpIo.Domain:010006": "यह उपयोगकर्ता पहले से ही इस संगठन का मालिक है!",
    "Volo.AbpIo.Domain:010007": "यह उपयोगकर्ता इस संगठन में पहले से ही एक डेवलपर है!",
    "Volo.AbpIo.Domain:010008": "अनुमत डेवलपर गणना कम नहीं हो सकती है तो वर्तमान डेवलपर गणना!",
    "Volo.AbpIo.Domain:010009": "अनुमत डेवलपर गणना 0 से कम नहीं हो सकती है!",
    "Volo.AbpIo.Domain:010010": "अधिकतम मैक पता गणना पार हो गई है!",
    "Volo.AbpIo.Domain:010011": "व्यक्तिगत लाइसेंस में 1 से अधिक डेवलपर नहीं हो सकते हैं!",
    "Volo.AbpIo.Domain:010012": "लाइसेंस की अवधि समाप्त होने के एक महीने बाद तक लाइसेंस नहीं बढ़ाया जा सकता है!",
    "Volo.AbpIo.Domain:020001": "इस NPM पैकेज को नहीं हटाया जा सका क्योंकि \"{NugetPackages}\" नुगेट पैकेज इस पैकेज पर निर्भर हैं।",
    "Volo.AbpIo.Domain:020002": "यह NPM पैकेज नहीं हटा सका क्योंकि \"{Modules}\" मॉड्यूल इस पैकेज का उपयोग कर रहे हैं।",
    "Volo.AbpIo.Domain:020003": "इस NPM पैकेज को नहीं हटाया जा सका क्योंकि \"{Modules}\" मॉड्यूल इस पैकेज का उपयोग कर रहे हैं और \"{NugetPackages}\" नुगेट पैकेज इस पैकेज पर निर्भर हैं।",
    "Volo.AbpIo.Domain:020004": "इस Nuget पैकेज को हटाया नहीं जा सका क्योंकि \"{Modules}\" मॉड्यूल इस पैकेज का उपयोग कर रहे हैं।",
    "Volo.AbpIo.Domain:030000": "आपने अपनी परीक्षण अवधि पहले ही पूरी कर ली है.",
    "Volo.AbpIo.Domain:030001": "इस संगठन का नाम पहले से मौजूद है.",
    "Volo.AbpIo.Domain:030002": "एक बार सक्रिय होने पर, आप परीक्षण लाइसेंस को -अनुरोधित- स्थिति में नहीं बदल सकते!",
    "Volo.AbpIo.Domain:030003": "ऐसी कोई स्थिति नहीं है!",
    "Volo.AbpIo.Domain:030004": "किसी अप्रत्याशित त्रुटि के कारण स्थिति नहीं बदली जा सकी!",
    "Volo.AbpIo.Domain:030005": "ट्रायल लाइसेंस -सक्रिय-स्थिति में होने पर आरंभ और समाप्ति तिथि को अपडेट किया जा सकता है!",
    "Volo.AbpIo.Domain:030006": "अंतिम तिथि आरंभ तिथि से बड़ी होनी चाहिए!",
    "Volo.AbpIo.Domain:030007": "यह परीक्षण लाइसेंस पहले ही सक्रिय किया जा चुका है!",
    "Volo.AbpIo.Domain:030008": "खरीदारी की तारीख केवल तभी निर्धारित की जा सकती है जब स्थिति -खरीदा- हो!",
    "Volo.AbpIo.Domain:030009": "उपयोगकर्ता नहीं मिला!",
    "Volo.AbpIo.Domain:030010": "ट्रायल लाइसेंस खरीदने के लिए, आपको सबसे पहले अपना ट्रायल लाइसेंस सक्रिय करना होगा!",
    "Volo.AbpIo.Domain:030011": "जब कोई ट्रायल लाइसेंस खरीदा जाता है तो आप उसे हटा नहीं सकते!",
    "Volo.AbpIo.Domain:030012": "एक उपयोगकर्ता केवल 1 निःशुल्क परीक्षण अवधि का हकदार है। आपने पहले ही अपना परीक्षण लाइसेंस उपयोग कर लिया है.",
    "Volo.AbpIo.Domain:030013": "सक्रिय लाइसेंस वाला उपयोगकर्ता परीक्षण लाइसेंस प्रारंभ नहीं कर सकता।",
    "Volo.AbpIo.Domain:040000": "टेलीमेट्री पहले से मौजूद है!",
    "Volo.AbpIo.Domain:070000": "संगठन के नाम में केवल लैटिन अक्षर, संख्याएँ, बिंदु और हाइफ़न हो सकते हैं!",
    "Volo.AbpIo.Domain:070001": "कंपनी के नाम में केवल लैटिन अक्षर, संख्याएँ, बिंदु, स्थान और हाइफ़न हो सकते हैं!",
    "WantToLearn?": "सीखना चाहते है?",
    "ReadyToGetStarted?": "आरंभ करने के लिए तैयार हैं?",
    "JoinOurCommunity": "हमारी संस्था से जुड़े",
    "GetStartedUpper": "शुरू हो जाओ",
    "ForkMeOnGitHub": "GitHub पर मेरे कांटा",
    "Features": "विशेषताएं",
    "GetStarted": "शुरू हो जाओ",
    "Documents": "दस्तावेज़",
    "Community": "समुदाय",
    "ContributionGuide": "योगदान गाइड",
    "Blog": "ब्लॉग",
    "Commercial": "व्यावसायिक",
    "MyAccount": "मेरा खाता",
    "Permission:License": "लाइसेंस",
    "Permission:UserInfo": "हमें जानकारी",
    "SeeDocuments": "दस्तावेज़ देखें",
    "Samples": "नमूने",
    "Framework": "ढांचा",
    "Support": "सहयोग",
    "FreeDDDBook": "मुफ्त डीडीडी ई-बुक",
    "New": "नया",
    "Volo.AbpIo.Domain:020005": "लाइसेंस विस्तार वर्ष {MinExtendLicenseYear} वर्ष (वर्षों) से कम और {MaxExtendLicenseYear} वर्ष (वर्षों) से अधिक नहीं हो सकता",
    "TrialLicensePeriodHasExpired": "आपके परीक्षण लाइसेंस की अवधि {0} दिन पहले समाप्त हो गई है।",
    "TrialLicensePeriodWillExpire": "आपके परीक्षण लाइसेंस की अवधि {0} दिनों में समाप्त हो जाएगी।",
    "TrialLicensePeriodExpireToday": "आपके परीक्षण लाइसेंस की अवधि आज समाप्त हो जाएगी।",
    "PurchaseNow": "अभी खरीदो!",
    "LatestReleaseLogs": "नवीनतम रिलीज़ लॉग",
    "RoadMap": "रोड मैप",
    "FAQ": "सामान्य प्रश्न",
    "SourceCode": "सोर्स कोड",
    "SeeAllPosts": "सभी पोस्ट देखें",
    "Contribute": "योगदान देना",
    "LiveDemo": "लाइव डेमो",
    "GetLicense": "लाइसेंस प्राप्त करें",
    "OpenSource": "खुला स्त्रोत",
    "WebApplication": "वेब अनुप्रयोग",
    "MeetTheABP": "एबीपी से मिलें",
    "CompleteWebDevelopment": "एक संपूर्ण वेब विकास",
    "Platform": "प्लैटफ़ॉर्म",
    "ABPDescription": "ASP.NET कोर के लिए वेब एप्लिकेशन विकास के लिए एक ओपन-सोर्स फ्रेमवर्क। यह सॉफ्टवेयर विकास की सर्वोत्तम प्रथाओं का पालन करके संपूर्ण बुनियादी ढांचा प्रदान करता है।",
    "StrongInfrastructure": "मजबूत बुनियादी ढांचा",
    "CompleteArchitecture": "संपूर्ण वास्तुकला",
    "DeveloperFocused": "डेवलपर केंद्रित",
    "ShareYourExperiences": "एबीपी फ्रेमवर्क के साथ अपने अनुभव साझा करें",
    "LatestPosts": "नवीनतम पोस्ट",
    "LatestVideos": "नवीनतम वीडियो",
    "Views": "दृश्य",
    "LearnLatestNewsAboutABPFramework": "एबीपी में होने वाली घटनाओं जैसे नई रिलीज़, मुफ़्त स्रोत, पोस्ट और बहुत कुछ के बारे में जानकारी प्राप्त करें।",
    "DeveloperTools": "डेवलपर उपकरण",
    "StartupTemplates": "स्टार्टअप टेम्पलेट्स",
    "ApplicationModules": "अनुप्रयोग मॉड्यूल",
    "UI": "यूआई",
    "Themes": "विषय-वस्तु",
    "Premium": "अधिमूल्य",
    "PrivacyPolicy": "गोपनीयता नीति",
    "TermsAndConditions": "नियम एवं शर्तें",
    "WouldLikeToReceiveMarketingMaterials": "मैं उत्पाद सौदे और विशेष ऑफ़र जैसी विपणन सामग्री प्राप्त करना चाहूंगा।",
    "JoinOurMarketingNewsletter": "हमारे मार्केटिंग न्यूज़लेटर से जुड़ें",
    "CommunityPrivacyPolicyConfirmation": "मैं नियम एवं शर्तों और <a class=\"text-white fw-6 text-decoration-underline opacity-50\" href=\"https://commercial.abp.io/Privacy\">गोपनीयता नीति</a> से सहमत हूं।",
    "WouldLikeToReceiveNotification": "मैं abp.io वेबसाइटों से नवीनतम समाचार प्राप्त करना चाहूंगा।",
    "CommercialNewsletterConfirmationMessage": "मैं <a class=\"text-white fw-6 text-decoration-underline opacity-50\" href=\"https://commercial.abp.io/TermsConditions\">नियम एवं शर्तों</a> और <a  class=\"text-white fw-6 text-decoration-underline opacity-50\" href=\"https://commercial.abp.io/Privacy\">गोपनीयता नीति</a> से सहमत हूं।",
    "FreeDDDEBook": "निःशुल्क डीडीडी ई-बुक",
    "AdditionalServices": "अतिरिक्त सेवाएं",
    "Learn": "सीखना",
    "AccountOverview": "खाता अवलोकन",
    "MyOrganizations": "मेरे संगठन",
    "MySupportQuestions": "मेरे समर्थन प्रश्न",
    "MyProfile": "मेरी प्रोफाइल",
    "Logout": "लॉग आउट",
    "Home": "घर",
    "Posts": "पदों",
    "Videos": "वीडियो",
    "JoinTheABPCommunity": "एबीपी समुदाय से जुड़ें",
    "SubmitYourPost": "अपनी पोस्ट सबमिट करें",
    "Modules": "मॉड्यूल",
    "Tools": "औजार",
    "Pricing": "मूल्य निर्धारण",
    "ChangeLogs": "लॉग बदलें",
    "SubscribeToNewsletter": "न्यूज़लैटर की सदस्यता लें",
    "SubscribeToNewsletterDescription": "एबीपी में होने वाली घटनाओं जैसे नई रिलीज़, मुफ़्त स्रोत, पोस्ट और बहुत कुछ के बारे में जानकारी प्राप्त करें।",
    "EmailAddress": "मेल पता",
    "Subscribe": "सदस्यता लें",
    "WelcomeToABP": "एबीपी में आपका स्वागत है",
    "EULA": "EULA",
    "ABPCommercialIntroductionMessage": "पूर्व-निर्मित एप्लिकेशन मॉड्यूल, उन्नत स्टार्टअप टेम्पलेट, तीव्र एप्लिकेशन डेवलपमेंट टूलिंग, पेशेवर यूआई थीम और प्रीमियम समर्थन।",
    "MasteringAbpFrameworkEBook": "एबीपी फ्रेमवर्क में महारत हासिल करना",
    "MasteringTheABPFrameworkExplanation": "एबीपी फ्रेमवर्क के निर्माता द्वारा लिखित, यह पुस्तक आपको फ्रेमवर्क और आधुनिक वेब एप्लिकेशन विकास तकनीकों की पूरी समझ हासिल करने में मदद करेगी।",
    "Speakers": "वक्ताओं",
    "PreviousEvents": "पिछली घटनाएँ",
    "WatchTheEvent": "घटना देखें",
    "RegisterNow": "अभी पंजीकरण करें",
    "ThereIsNoEvent": "कोई आयोजन नहीं है.",
    "Events": "आयोजन",
    "Volo.AbpIo.Domain:080000": "&quot;{Name}&quot; नाम से पहले से ही एक खरीद वस्तु मौजूद है",
    "MasteringAbpFrameworkBook": "पुस्तक: एबीपी फ्रेमवर्क में महारत हासिल करना",
    "ABPIO-CommonPreferenceDefinition": "एबीपी प्लेटफ़ॉर्म के बारे में नवीनतम समाचार प्राप्त करें जैसे नए पोस्ट, ईवेंट और बहुत कुछ।",
    "BuiltOn": "बनाया गया",
    "AbpFramework": "एबीपी फ्रेमवर्क",
    "Volo.AbpIo.Domain:080001": "प्रारंभ समय समाप्ति समय से अधिक नहीं हो सकता",
    "Enum:BookType:0": "एबीपी फ्रेमवर्क में महारत हासिल करना",
    "Enum:PurchasePlatform:0": "वीरांगना",
    "Enum:PurchasePlatform:1": "पैकेट",
    "Copied": "नकल की गई!",
    "CouldNotCopy": "की नकल नहीं कर सकता!",
    "CopyNotSupportByYourBrowser": "यह सुविधा आपके द्वारा उपयोग किए जा रहे ब्राउज़र में काम नहीं करती है.",
    "City": "शहर",
    "ZipCode": "ज़िप कोड",
    "Address": "पता",
    "Homepage": "मुखपृष्ठ",
    "Year": "वर्ष",
    "Year_Plural": "साल",
    "Copyright": "कॉपीराइट © <a href=\"{0}\" target=\"_blank\">{1}</a>",
    "DomainDrivenDesign": "डोमेन संचालित डिज़ाइन",
    "CrossCuttingConcerns": "फिल्म आदि में दृश्यों के संपादन संबंधी चिंताएं",
    "AbpCommunity": "एबीपी समुदाय",
    "Footer_GithubStarCount": "{0} GitHub पर सितारे",
    "Footer_NugetDownloadCount": "{0} NuGet पर डाउनलोड",
    "AbpDescription": "एबीपी एक ओपन सोर्स एप्लिकेशन फ्रेमवर्क है जो एएसपीनेट कोर आधारित वेब एप्लिकेशन डेवलपमेंट पर केंद्रित है। अपने आप को दोहराएँ नहीं, अपने व्यवसाय कोड पर ध्यान केंद्रित करें।",
    "Layout_AbpFramework_MetaTitle": "एबीपी फ्रेमवर्क | ASP.NET कोर के लिए ओपन सोर्स वेब एप्लिकेशन फ्रेमवर्क",
    "CommunityTalks_CountdownDays": "दिन",
    "CommunityTalks_CountdownHours": "घंटे",
    "CommunityTalks_CountdownMinutes": "मिन",
    "CommunityTalks_CountdownSeconds": "सेकंड",
    "SeePreviousEvents": "पिछली घटनाएँ देखें",
    "CookieConsent_Accept": "स्वीकार करना",
    "CookieConsent_Explanation_1": "हम अपनी वेबसाइट पर आपको सर्वोत्तम अनुभव देने के लिए कुकीज़ का उपयोग करते हैं।",
    "CookieConsent_Explanation_2": "यदि आप ब्राउज़ करना जारी रखते हैं, तो आप हमारी <a href=\"@Url.Page(\"/Privacy\")\">गोपनीयता नीति और कुकी नीति से सहमत हैं।</a> .",
    "Error_Page_400_Title": "अनुरोधित पृष्ठ को परोसने में समस्या थी.",
    "Error_Page_400_Description_1": "आमतौर पर इसका मतलब यह है कि आपके अनुरोध को संसाधित करते समय एक अप्रत्याशित त्रुटि हुई।",
    "Error_Page_400_Description_2": "यदि समस्या बनी रहती है, तो <a href=\"mailto:info@abp.io\">info@abp.io</a> पर हमसे संपर्क करें और हम आपको सही रास्ते पर लाने में मदद करेंगे।",
    "GoToHomepage": "मुखपृष्ठ प्र जाएं",
    "Error_Page_404_Title": "पृष्ठ नहीं मिला!",
    "Error_Page_404_Description_1": "यह वह वेब पेज नहीं है जिसे आप ढूंढ रहे हैं।",
    "Error_Page_500_Title": "ऐसा लगता है जैसे कुछ गलत हो गया!",
    "Error_Page_500_Description_1": "हम इन त्रुटियों को स्वचालित रूप से ट्रैक करते हैं, लेकिन यदि समस्या बनी रहती है तो बेझिझक संपर्क करें<br /> संपर्क करें। इस बीच, ताज़ा करने का प्रयास करें।",
    "Error_Page_500_Description_2": "हमसे <a href=\"mailto:info@abp.io\" target=\"_blank\">info@abp.io</a> पर संपर्क करें।",
    "Books": "पुस्तकें",
    "ABPDiscordServer": "एबीपी डिस्कॉर्ड सर्वर",
    "ABPCommunityTalks": "एबीपी समुदाय वार्ता",
    "ABPCommunityPosts": "एबीपी सामुदायिक पोस्ट",
    "BuyAndGetMonths": "12 महीने खरीदें, <span>14 महीने पाएं!</span>",
    "GetYourDeal": "अपना सौदा प्राप्त करें",
    "BuyOrRenewLicense": "अभी लाइसेंस खरीदें या नवीनीकृत करें और 2 अतिरिक्त महीने प्राप्त करें!",
    "BuyOrRenewLicenseToGetExtra2Months": "अभी लाइसेंस खरीदें या नवीनीकृत करें और 2 अतिरिक्त महीने प्राप्त करें! जल्दी करो! ⏰ अंतिम दिन: {0}",
    "HurryUp": "जल्दी करो!",
    "LastDay": "अंतिम दिन: {0}",
    "BuyNewLicenseBetweenDatesToGetBenefit": "अतिरिक्त 2 महीनों का लाभ पाने के लिए {0} और {1} के बीच नया लाइसेंस खरीदें!",
    "CheckAllCommunityTalks": "सभी सामुदायिक पोस्ट जांचें",
    "ReadMore": "और पढ़ें",
    "ContinueReading": "जारी रखें पढ़ रहे हैं",
    "Post": "डाक",
    "ExploreTheContentsCreatedByTheCoreABPTeamAndTheABPCommunity": "कोर एबीपी टीम और एबीपी समुदाय द्वारा बनाई गई सामग्री का अन्वेषण करें।",
    "WelcomeFallCampaign": "पतन अभियान का स्वागत है!",
    "GiveAwayForNewPurchases": "नई खरीद के लिए एप्लिकेशन डेवलपमेंट क्लासरूम प्रशिक्षण दिया जाएगा!",
    "BlackFriday": "<strong>ब्लैक</strong> <span>फ्राइडे</span>",
    "ValidForExistingCustomers": "के लिए भी मान्य है<br> मौजूदा ग्राहक!",
    "CampaignBetweenDates": "{0} से<br> {1} को",
    "SaveUpTo": "<strong>${0}K</strong> तक <span>बचाएं</span>",
    "ImplementingDDD": "डोमेन संचालित डिज़ाइन लागू करना",
    "ExploreTheEBook": "ई-पुस्तक का अन्वेषण करें",
    "ExploreTheBook": "पुस्तक का अन्वेषण करें",
    "ConsultantType": "परामर्श प्रकार",
    "Expert": "एबीपी एक्सपर्ट",
    "Partner": "एबीपी पार्टनर",
    "Industry": "उद्योग",
    "Location": "जगह",
    "Contact": "संपर्क",
    "Partner_Year": "साझेदारी वर्ष",
    "Info": "जानकारी",
    "SpokenLanguages": "बोली जाने वाली भाषाएं",
    "SocialMedia": "सामाजिक मीडिया",
    "Activity": "गतिविधि",
    "Type": "प्रकार",
    "Contribution": "योगदान",
    "WhoWeAre": "हम जो हैं",
    "Icons": "माउस",
    "Url": "यूआरएल",
    "Icon": "आइकन",
    "RecentActivities": "हाल की गतिविधियां",
    "SpringCampaign": "स्वागत<br> वसंत बिक्री!",
    "SpringCampaign2": "<span>सीमित<br> समय प्रस्ताव!</span>",
    "AboutUs": "हमारे बारे में",
    "HowItWorks": "यह काम किस प्रकार करता है?",
    "ReleaseNotes": "रिलीज नोट्स",
    "DetailedChangeNotes": "विस्तृत परिवर्तन नोट्स",
    "SeeTrainings": "प्रशिक्षण देखें",
    "NoContent": "कोई सामग्री नहीं है",
    "More": "अधिक",
    "WhyABPIOPlatform": "ABP.IO प्लेटफार्म क्यों?",
    "AbpStudio": "एबीपी स्टूडियो",
    "ExtraMonths": "{0} <span>अतिरिक्त महीने</span>",
    "RSS": "आरएसएस",
    "RSSFeed": "आरएसएस फीड",
    "Articles": "सामग्री",
    "Organizations": "संगठनों",
    "ManageAccount": "खाते का प्रबंधन करें",
    "CommunityProfile": "सामुदायिक प्रोफ़ाइल",
    "BlogProfile": "ब्लॉग प्रोफ़ाइल",
    "Tickets": "टिकट",
    "MeetTheABPCommunity": "ABP से मिलें <span class=\"gradient-community\">समुदाय</span>",
    "DisplayName:CommunityIndexPagePoll": "सामुदायिक अनुभाग मतदान",
    "OrganizationOverview": "संगठन अवलोकन",
    "EmailPreferences": "ईमेल प्राथमिकताएं",
    "VideoCourses": "आवश्यक वीडियो",
    "Resources": "संसाधन",
    "DoYouAgreePrivacyPolicy": "क्लिक करके <b>सदस्यता लें</b> जिस बटन से आप सहमत हैं <a href=\"https://account.abp.io/Account/TermsConditions\">शर्तें</a> और <a href=\"https://account.abp.io/Account/Privacy\">गोपनीयता नीति</a>.",
    "PromotionalOffers": "प्रोमोशनल ऑफ़र",
    "PromotionalOffersDefinition": "छूट, मौसमी अभियान, आदि।",
    "EventsDefinition": "सामुदायिक वार्ता, वेबिनार, ABP .NET सम्मेलन, आदि।",
    "ReleaseNotesDefinition": "ABP.IO प्लेटफ़ॉर्म रिलीज़, नए उत्पाद, आदि।",
    "Newsletter": "समाचार पत्रिका",
    "NewsletterDefinition": "ब्लॉग पोस्ट, सामुदायिक समाचार, आदि।",
    "AbpConferenceDescription": "ABP Conference .NET डेवलपर्स के लिए समुदाय से सीखने और जुड़ने के लिए एक आभासी कार्यक्रम है।"
  }
}