{
  "culture": "el",
  "texts": {
    "Languages": "Γλώσσες",
    "AreYouSure": "Είσαι σίγουρος;",
    "Cancel": "Ακύρωση",
    "Clear": "Εκκαθάριση",
    "Yes": "Ναι",
    "No": "όχι",
    "Ok": "Οκ",
    "Close": "Κλείσιμο",
    "Save": "Αποθήκευση",
    "SavingWithThreeDot": "Αποθηκεύεται...",
    "Actions": "Ενέργειες",
    "Delete": "Διαγραφή",
    "CreatedSuccessfully": "Δημιουργήθηκε με επιτυχία",
    "SavedSuccessfully": "Αποθηκεύτηκε με επιτυχία",
    "DeletedSuccessfully": "Διαγράφηκε με επιτυχία",
    "Edit": "Επεξεργασία",
    "Refresh": "Ανανέωση",
    "Language": "Γλώσσα",
    "LoadMore": "Φόρτωση περισσοτέρων",
    "ProcessingWithThreeDot": "Επεξεργασία...",
    "LoadingWithThreeDot": "Φόρτωση...",
    "Welcome": "Καλώς ήρθατε",
    "Login": "Σύνδεση",
    "Register": "Εγγραφή",
    "Logout": "Αποσύνδεση",
    "Submit": "Υποβολή",
    "Back": "Πίσω",
    "PagerSearch": "Αναζήτηση",
    "PagerNext": "Επόμενο",
    "PagerPrevious": "Προηγούμενο",
    "PagerFirst": "Πρώτο",
    "PagerLast": "Τελευταίο",
    "PagerInfo": "Εμφάνιση _START_ έως _END_ από _TOTAL_ εγγραφές",
    "PagerInfo{0}{1}{2}": "Εμφάνιση {0} έως {1} από {2} εγγραφές",
    "PagerInfoEmpty": "Εμφάνιση 0 έως 0 από 0 εγγραφές",
    "PagerInfoFiltered": "(φιλτραρισμένο από _MAX_ συνολικές εγγραφές)",
    "NoDataAvailableInDatatable": "Δεν υπάρχουν διαθέσιμα δεδομένα",
    "ErrorLoadingDatatable": "Παρουσιάστηκε σφάλμα κατά τη διάρκεια του αιτήματος. Ελέγξτε το μήνυμα για λεπτομέρειες.",
    "Total": "Σύνολο",
    "Selected": "Έχει γίνει επιλογή",
    "PagerShowMenuEntries": "Εμφάνιση στοιχείων _MENU_",
    "DatatableActionDropdownDefaultText": "Ενέργειες",
    "ChangePassword": "Αλλαγή Κωδικού",
    "PersonalInfo": "Το προφίλ μου",
    "AreYouSureYouWantToCancelEditingWarningMessage": "Έχετε μη αποθηκευμένες αλλαγές.",
    "GoHomePage": "Μετάβαση στην αρχική σελίδα",
    "GoBack": "Πίσω",
    "Search": "Αναζήτηση",
    "ItemWillBeDeletedMessageWithFormat": "Το {0} θα διαγραφεί",
    "ItemWillBeDeletedMessage": "Αυτό το στοιχείο θα διαγραφεί!",
    "ManageYourAccount": "Διαχείριση Λογαριασμού",
    "OthersGroup": "άλλος",
    "Today": "Σήμερα",
    "Apply": "Ισχύουν"
  }
}
